lotrpc/__init__.py
lotrpc/client.py
lotrpc/clsrv.py
lotrpc/dispatcher.py
lotrpc/proxy.py
lotrpc/proxyauth.py
lotrpc/rpcgen.py
lotrpc/server.py
lotrpc/version.py
lotrpc/aioxml/__init__.py
lotrpc/aioxml/rpc.py
lotrpc/grpc/__init__.py
lotrpc/grpc/rpc.py
lotrpc/json/__init__.py
lotrpc/json/rpc.py
lotrpc/mp/__init__.py
lotrpc/mp/rpc.py
lotrpc/msgpack/__init__.py
lotrpc/msgpack/rpc.py
lotrpc/sunrpc/__init__.py
lotrpc/sunrpc/parse.py
lotrpc/sunrpc/rpc.py
lotrpc/sunrpc/rpcgen.py
lotrpc/xml/__init__.py
lotrpc/xml/rpc.py
lotrpc/zero/__init__.py
lotrpc/zero/rpc.py
lotrpc-0.1.2.dist-info/LICENSE
lotrpc-0.1.2.dist-info/METADATA
lotrpc-0.1.2.dist-info/WHEEL
lotrpc-0.1.2.dist-info/entry_points.txt
lotrpc-0.1.2.dist-info/top_level.txt
lotrpc-0.1.2.dist-info/RECORD
