Metadata-Version: 2.1
Name: lotrpc
Version: 0.1.2
Summary: RPC abstraction layer
Home-page: https://github.com/wtnb75/lotrpc
Author: Takashi WATANABE
Author-email: wtnb75@gmail.com
License: MIT
Keywords: rpc proxy grpc zerorpc json xml messagepack
Platform: UNKNOWN
Classifier: Development Status :: 3 - Alpha
Classifier: Intended Audience :: Developers
Classifier: License :: OSI Approved :: MIT License
Classifier: Topic :: Communications
Classifier: Programming Language :: Python :: 3
Requires-Python: >=3
Requires-Dist: msgpack-rpc-python
Requires-Dist: requests
Requires-Dist: tornado (<5)
Requires-Dist: grpcio-tools
Requires-Dist: grpcio
Requires-Dist: click
Requires-Dist: zerorpc
Requires-Dist: mprpc
Requires-Dist: Benchmarker
Requires-Dist: ply
Requires-Dist: bcrypt
Requires-Dist: aiohttp-xmlrpc
Requires-Dist: PyYAML
Requires-Dist: aiohttp-jsonrpc
Provides-Extra: development
Requires-Dist: jupyter ; extra == 'development'
Requires-Dist: wheel ; extra == 'development'
Requires-Dist: twine ; extra == 'development'
Requires-Dist: mypy ; extra == 'development'
Requires-Dist: pyflakes ; extra == 'development'
Requires-Dist: pycodestyle ; extra == 'development'
Requires-Dist: nose ; extra == 'development'
Requires-Dist: coverage ; extra == 'development'
